oarepo_invenio_model/__init__.py
oarepo_invenio_model/version.py
oarepo_invenio_model/datamodels/__init__.py
oarepo_invenio_model/datamodels/invenio-record-v3.0.0.json5
oarepo_invenio_model/included_mappings/v7/invenio-v3.0.0.json
oarepo_invenio_model/jsonschemas/__init__.py
oarepo_invenio_model/jsonschemas/invenio-v3.0.0.json
oarepo_invenio_model/marshmallow/__init__.py
oarepo_invenio_model-3.0.2.dist-info/LICENSE
oarepo_invenio_model-3.0.2.dist-info/METADATA
oarepo_invenio_model-3.0.2.dist-info/WHEEL
oarepo_invenio_model-3.0.2.dist-info/entry_points.txt
oarepo_invenio_model-3.0.2.dist-info/top_level.txt
oarepo_invenio_model-3.0.2.dist-info/RECORD
