Metadata-Version: 2.1
Name: oarepo-invenio-model
Version: 3.0.2
Summary: Invenio data model for OARepo
Home-page: https://github.com/oarepo/invenio_oarepo_invenio_model
Author: Miroslav Simek
Author-email: miroslav.simek@vscht.cz
License: MIT
Platform: any
Classifier: Environment :: Web Environment
Classifier: Intended Audience :: Developers
Classifier: License :: OSI Approved :: MIT License
Classifier: Operating System :: OS Independent
Classifier: Programming Language :: Python
Classifier: Topic :: Internet :: WWW/HTTP :: Dynamic Content
Classifier: Topic :: Software Development :: Libraries :: Python Modules
Classifier: Programming Language :: Python :: 2
Classifier: Programming Language :: Python :: 2.7
Classifier: Programming Language :: Python :: 3
Classifier: Programming Language :: Python :: 3.5
Classifier: Development Status :: 4 - Beta
License-File: LICENSE
Provides-Extra: build
Requires-Dist: oarepo-model-builder ; extra == 'build'
Provides-Extra: tests
Requires-Dist: oarepo-validate ; extra == 'tests'
Requires-Dist: oarepo[tests] ; extra == 'tests'
